setup.py
console_calendar/__init__.py
console_calendar/main.py
console_calendar/version.py
console_calendar.egg-info/PKG-INFO
console_calendar.egg-info/SOURCES.txt
console_calendar.egg-info/dependency_links.txt
console_calendar.egg-info/not-zip-safe
console_calendar.egg-info/requires.txt
console_calendar.egg-info/top_level.txt
console_calendar/bin/__init__.py
console_calendar/bin/concal