Metadata-Version: 1.1
Name: console-calendar
Version: 0.1.1
Summary: A calendar working in console.
Home-page: https://github.com/acro5piano/console_calendar
Author: Kazuya Gosho
Author-email: ketsume0211@gmail.com
License: UNKNOWN
Platform: UNKNOWN
Classifier: Programming Language :: Python :: 2.7
Classifier: Programming Language :: Python :: 3.4
Classifier: Programming Language :: Python :: 3.5
